cunitpy/__init__.py
cunitpy/cunitpy.py
cunitpy-0.0.4.dist-info/LICENSE
cunitpy-0.0.4.dist-info/METADATA
cunitpy-0.0.4.dist-info/WHEEL
cunitpy-0.0.4.dist-info/top_level.txt
cunitpy-0.0.4.dist-info/RECORD
