Metadata-Version: 2.1
Name: cunitpy
Version: 0.0.4
Summary: A universal converter package
Home-page: https://github.com/LazimR/CunitPy
Author: Lázaro Claubert
Author-email: lazimrclaubert@gmail.com
Maintainer: Kennedy Souza
Maintainer-email: kennedo160@gmail.com
Classifier: Programming Language :: Python :: 3
Classifier: License :: OSI Approved :: GNU General Public License v3 (GPLv3)
Classifier: Operating System :: OS Independent
Requires-Python: >=3.8
License-File: LICENSE
